setup.cfg
setup.py
lib/smtpcom/__init__.py
lib/smtpcom/config.py
lib/smtpcom/router.py
lib/smtpcom/sendapi/__init__.py
lib/smtpcom/sendapi/api.py
lib/smtpcom/sendapi/campaign.py
lib/smtpcom/sendapi/report.py
lib/smtpcom/sendapi/send.py
lib/smtpcom/sendapi/template.py
lib/smtpcom_sendapi.egg-info/PKG-INFO
lib/smtpcom_sendapi.egg-info/SOURCES.txt
lib/smtpcom_sendapi.egg-info/dependency_links.txt
lib/smtpcom_sendapi.egg-info/requires.txt
lib/smtpcom_sendapi.egg-info/top_level.txt
lib/smtpcom_sendapi.egg-info/zip-safe