Metadata-Version: 1.0
Name: smtpcom-sendapi
Version: 1.01
Summary: SMTP SendApi
Home-page: http://smtp.com/
Author: Yand Kornienko
Author-email: yana@smtp.com
License: Copyright 2015, SMTP.COM.
Platform: UNKNOWN
